{
  "users": [
    {
      "id": 1,
      "first_name": "Margery",
      "last_name": "McGrah",
      "email": "mmcgrah0@yelp.com",
      "gender": "Female",
      "city": "Chełm"
    },
    {
      "id": 2,
      "first_name": "Cedric",
      "last_name": "Tichelaar",
      "email": "ctichelaar1@reddit.com",
      "gender": "Male",
      "city": "Niwiska"
    },
    {
      "id": 3,
      "first_name": "Reilly",
      "last_name": "Napton",
      "email": "rnapton2@list-manage.com",
      "gender": "Male",
      "city": "Ra-ngae"
    },
    {
      "id": 4,
      "first_name": "Burch",
      "last_name": "Muckley",
      "email": "bmuckley3@feedburner.com",
      "gender": "Male",
      "city": "Haveli"
    },
    {
      "id": 5,
      "first_name": "Mathias",
      "last_name": "Harty",
      "email": "mharty4@about.me",
      "gender": "Male",
      "city": "Two Hills"
    },
    {
      "id": 6,
      "first_name": "Arel",
      "last_name": "Beggi",
      "email": "abeggi5@youtu.be",
      "gender": "Male",
      "city": "Cairani"
    },
    {
      "id": 7,
      "first_name": "Tracy",
      "last_name": "Segrave",
      "email": "tsegrave6@noaa.gov",
      "gender": "Female",
      "city": "Wenbi"
    },
    {
      "id": 8,
      "first_name": "Raquel",
      "last_name": "Phettiplace",
      "email": "rphettiplace7@oracle.com",
      "gender": "Female",
      "city": "Niort"
    },
    {
      "id": 9,
      "first_name": "Fawne",
      "last_name": "Algy",
      "email": "falgy8@hud.gov",
      "gender": "Female",
      "city": "Al ‘Aqabah"
    },
    {
      "id": 10,
      "first_name": "Dahlia",
      "last_name": "Littlepage",
      "email": "dlittlepage9@123-reg.co.uk",
      "gender": "Female",
      "city": "Batulawang"
    },
    {
      "id": 11,
      "first_name": "Adriane",
      "last_name": "Butters",
      "email": "abuttersa@va.gov",
      "gender": "Female",
      "city": "Sigavé"
    },
    {
      "id": 12,
      "first_name": "Leeanne",
      "last_name": "Penhalurick",
      "email": "lpenhalurickb@europa.eu",
      "gender": "Female",
      "city": "Alice"
    },
    {
      "id": 13,
      "first_name": "Isabeau",
      "last_name": "Birckmann",
      "email": "ibirckmannc@china.com.cn",
      "gender": "Female",
      "city": "Chatou"
    },
    {
      "id": 14,
      "first_name": "Hodge",
      "last_name": "Dulieu",
      "email": "hdulieud@so-net.ne.jp",
      "gender": "Male",
      "city": "Partizansk"
    },
    {
      "id": 15,
      "first_name": "Sheff",
      "last_name": "Brittles",
      "email": "sbrittlese@tiny.cc",
      "gender": "Male",
      "city": "Kuantan"
    },
    {
      "id": 16,
      "first_name": "Evvy",
      "last_name": "McCafferty",
      "email": "emccaffertyf@nymag.com",
      "gender": "Female",
      "city": "Świdnica"
    },
    {
      "id": 17,
      "first_name": "Vince",
      "last_name": "Mart",
      "email": "vmartg@godaddy.com",
      "gender": "Male",
      "city": "Salvacion"
    },
    {
      "id": 18,
      "first_name": "Lenka",
      "last_name": "Lorne",
      "email": "llorneh@51.la",
      "gender": "Female",
      "city": "Al Ḩawātah"
    },
    {
      "id": 19,
      "first_name": "Baudoin",
      "last_name": "Van Niekerk",
      "email": "bvanniekerki@alibaba.com",
      "gender": "Male",
      "city": "Kharbathā Banī Ḩārith"
    },
    {
      "id": 20,
      "first_name": "Betsy",
      "last_name": "Sleicht",
      "email": "bsleichtj@nydailynews.com",
      "gender": "Female",
      "city": "Skrwilno"
    },
    {
      "id": 21,
      "first_name": "Happy",
      "last_name": "Owbrick",
      "email": "howbrickk@last.fm",
      "gender": "Female",
      "city": "Juancheng"
    },
    {
      "id": 22,
      "first_name": "Aeriell",
      "last_name": "Ferraraccio",
      "email": "aferraracciol@whitehouse.gov",
      "gender": "Female",
      "city": "Ibitinga"
    },
    {
      "id": 23,
      "first_name": "Ulrica",
      "last_name": "Han",
      "email": "uhanm@nsw.gov.au",
      "gender": "Female",
      "city": "Września"
    },
    {
      "id": 24,
      "first_name": "Iris",
      "last_name": "Deeny",
      "email": "ideenyn@mail.ru",
      "gender": "Female",
      "city": "Kumla"
    },
    {
      "id": 25,
      "first_name": "Garek",
      "last_name": "Hursthouse",
      "email": "ghursthouseo@hc360.com",
      "gender": "Male",
      "city": "Tambobamba"
    },
    {
      "id": 26,
      "first_name": "Fidole",
      "last_name": "Brandrick",
      "email": "fbrandrickp@washington.edu",
      "gender": "Male",
      "city": "Sarandi"
    },
    {
      "id": 27,
      "first_name": "Verene",
      "last_name": "Fortescue",
      "email": "vfortescueq@psu.edu",
      "gender": "Female",
      "city": "Widorokandang"
    },
    {
      "id": 28,
      "first_name": "Kathi",
      "last_name": "Vest",
      "email": "kvestr@apache.org",
      "gender": "Female",
      "city": "Monterrey"
    },
    {
      "id": 29,
      "first_name": "Edith",
      "last_name": "Yeiles",
      "email": "eyeiless@mapquest.com",
      "gender": "Female",
      "city": "Salavat"
    },
    {
      "id": 30,
      "first_name": "Barney",
      "last_name": "Ethridge",
      "email": "bethridget@pcworld.com",
      "gender": "Male",
      "city": "Bombarral"
    },
    {
      "id": 31,
      "first_name": "Claire",
      "last_name": "McErlaine",
      "email": "cmcerlaineu@umich.edu",
      "gender": "Female",
      "city": "Yuzawa"
    },
    {
      "id": 32,
      "first_name": "Roma",
      "last_name": "Leopold",
      "email": "rleopoldv@mapy.cz",
      "gender": "Male",
      "city": "Hinlayagan Ilaud"
    },
    {
      "id": 33,
      "first_name": "Bo",
      "last_name": "Olliffe",
      "email": "bolliffew@state.gov",
      "gender": "Male",
      "city": "Torkanivka"
    },
    {
      "id": 34,
      "first_name": "Reube",
      "last_name": "Robke",
      "email": "rrobkex@wix.com",
      "gender": "Bigender",
      "city": "Kultayevo"
    },
    {
      "id": 35,
      "first_name": "Abramo",
      "last_name": "Pietasch",
      "email": "apietaschy@cbslocal.com",
      "gender": "Male",
      "city": "Jieshui"
    },
    {
      "id": 36,
      "first_name": "Lil",
      "last_name": "Dakhov",
      "email": "ldakhovz@netlog.com",
      "gender": "Female",
      "city": "Libato"
    },
    {
      "id": 37,
      "first_name": "Verna",
      "last_name": "Gozard",
      "email": "vgozard10@yolasite.com",
      "gender": "Female",
      "city": "Yingyang"
    },
    {
      "id": 38,
      "first_name": "Emogene",
      "last_name": "Janisson",
      "email": "ejanisson11@rakuten.co.jp",
      "gender": "Female",
      "city": "Khiv"
    },
    {
      "id": 39,
      "first_name": "Goran",
      "last_name": "Gerger",
      "email": "ggerger12@house.gov",
      "gender": "Genderqueer",
      "city": "Wakduwa’ Barat"
    },
    {
      "id": 40,
      "first_name": "Herman",
      "last_name": "Heers",
      "email": "hheers13@prnewswire.com",
      "gender": "Male",
      "city": "Río de Jesús"
    },
    {
      "id": 41,
      "first_name": "Marybelle",
      "last_name": "Jozefowicz",
      "email": "mjozefowicz14@google.it",
      "gender": "Female",
      "city": "Belverde"
    },
    {
      "id": 42,
      "first_name": "Alonso",
      "last_name": "Duce",
      "email": "aduce15@tiny.cc",
      "gender": "Male",
      "city": "Likino-Dulevo"
    },
    {
      "id": 43,
      "first_name": "Arlan",
      "last_name": "Lewis",
      "email": "alewis16@wix.com",
      "gender": "Male",
      "city": "Anguera"
    },
    {
      "id": 44,
      "first_name": "Eziechiele",
      "last_name": "Robberecht",
      "email": "erobberecht17@reddit.com",
      "gender": "Male",
      "city": "New York City"
    },
    {
      "id": 45,
      "first_name": "Maurie",
      "last_name": "Nanninini",
      "email": "mnanninini18@live.com",
      "gender": "Male",
      "city": "Wukari"
    },
    {
      "id": 46,
      "first_name": "Elvina",
      "last_name": "Schenkel",
      "email": "eschenkel19@cloudflare.com",
      "gender": "Female",
      "city": "Ogōri-shimogō"
    },
    {
      "id": 47,
      "first_name": "Selig",
      "last_name": "Matuschek",
      "email": "smatuschek1a@biglobe.ne.jp",
      "gender": "Male",
      "city": "Cabeça Gorda"
    },
    {
      "id": 48,
      "first_name": "Ben",
      "last_name": "Whitelaw",
      "email": "bwhitelaw1b@pcworld.com",
      "gender": "Male",
      "city": "Boafeo"
    },
    {
      "id": 49,
      "first_name": "Merilee",
      "last_name": "Taffrey",
      "email": "mtaffrey1c@ucoz.ru",
      "gender": "Female",
      "city": "Mutatá"
    },
    {
      "id": 50,
      "first_name": "Valentin",
      "last_name": "Roden",
      "email": "vroden1d@diigo.com",
      "gender": "Male",
      "city": "Aileu"
    },
    {
      "id": 51,
      "first_name": "Essy",
      "last_name": "Guiden",
      "email": "eguiden1e@netvibes.com",
      "gender": "Female",
      "city": "Caringin"
    },
    {
      "id": 52,
      "first_name": "Udall",
      "last_name": "Johnke",
      "email": "ujohnke1f@yelp.com",
      "gender": "Male",
      "city": "Chino"
    },
    {
      "id": 53,
      "first_name": "Odell",
      "last_name": "Wiltshear",
      "email": "owiltshear1g@hostgator.com",
      "gender": "Male",
      "city": "Lunang"
    },
    {
      "id": 54,
      "first_name": "Berny",
      "last_name": "Huggen",
      "email": "bhuggen1h@reference.com",
      "gender": "Non-binary",
      "city": "Hukou"
    },
    {
      "id": 55,
      "first_name": "Kyle",
      "last_name": "Ridoutt",
      "email": "kridoutt1i@ustream.tv",
      "gender": "Male",
      "city": "Cabinteely"
    },
    {
      "id": 56,
      "first_name": "Katleen",
      "last_name": "Boulton",
      "email": "kboulton1j@altervista.org",
      "gender": "Female",
      "city": "Lyamino"
    },
    {
      "id": 57,
      "first_name": "Richardo",
      "last_name": "Ussher",
      "email": "russher1k@engadget.com",
      "gender": "Male",
      "city": "Angers"
    },
    {
      "id": 58,
      "first_name": "Erastus",
      "last_name": "Stannion",
      "email": "estannion1l@archive.org",
      "gender": "Male",
      "city": "Kotabaru"
    },
    {
      "id": 59,
      "first_name": "Lynna",
      "last_name": "MacNeil",
      "email": "lmacneil1m@oracle.com",
      "gender": "Female",
      "city": "Kadyy"
    },
    {
      "id": 60,
      "first_name": "Crystal",
      "last_name": "Matzel",
      "email": "cmatzel1n@businessinsider.com",
      "gender": "Female",
      "city": "Futian"
    },
    {
      "id": 61,
      "first_name": "Royall",
      "last_name": "McCarthy",
      "email": "rmccarthy1o@ask.com",
      "gender": "Non-binary",
      "city": "Montpellier"
    },
    {
      "id": 62,
      "first_name": "Othilia",
      "last_name": "Priter",
      "email": "opriter1p@archive.org",
      "gender": "Genderfluid",
      "city": "Biaoxi"
    },
    {
      "id": 63,
      "first_name": "Domenic",
      "last_name": "Fearick",
      "email": "dfearick1q@nih.gov",
      "gender": "Male",
      "city": "Xiadahe"
    },
    {
      "id": 64,
      "first_name": "Wald",
      "last_name": "Paver",
      "email": "wpaver1r@cbc.ca",
      "gender": "Male",
      "city": "Benzilan"
    },
    {
      "id": 65,
      "first_name": "Hyacinthe",
      "last_name": "Guppey",
      "email": "hguppey1s@chron.com",
      "gender": "Female",
      "city": "Verkhnevilyuysk"
    },
    {
      "id": 66,
      "first_name": "Norbert",
      "last_name": "Malden",
      "email": "nmalden1t@foxnews.com",
      "gender": "Male",
      "city": "Blizne"
    },
    {
      "id": 67,
      "first_name": "Jacquelin",
      "last_name": "Riding",
      "email": "jriding1u@dagondesign.com",
      "gender": "Female",
      "city": "Além"
    },
    {
      "id": 68,
      "first_name": "Hadley",
      "last_name": "Dumingo",
      "email": "hdumingo1v@mlb.com",
      "gender": "Male",
      "city": "Gualeguay"
    },
    {
      "id": 69,
      "first_name": "Thomasin",
      "last_name": "Tokley",
      "email": "ttokley1w@discovery.com",
      "gender": "Female",
      "city": "Sibaté"
    },
    {
      "id": 70,
      "first_name": "Greggory",
      "last_name": "Tedahl",
      "email": "gtedahl1x@ebay.com",
      "gender": "Male",
      "city": "Zhenzhushan"
    },
    {
      "id": 71,
      "first_name": "Sheeree",
      "last_name": "McCormack",
      "email": "smccormack1y@domainmarket.com",
      "gender": "Female",
      "city": "Bang Racham"
    },
    {
      "id": 72,
      "first_name": "Augustina",
      "last_name": "Ivashov",
      "email": "aivashov1z@youtu.be",
      "gender": "Female",
      "city": "Huarong"
    },
    {
      "id": 73,
      "first_name": "Cully",
      "last_name": "Pitblado",
      "email": "cpitblado20@histats.com",
      "gender": "Male",
      "city": "Dolores"
    },
    {
      "id": 74,
      "first_name": "Pablo",
      "last_name": "Brody",
      "email": "pbrody21@gmpg.org",
      "gender": "Male",
      "city": "Shibushi"
    },
    {
      "id": 75,
      "first_name": "Lonnard",
      "last_name": "Camp",
      "email": "lcamp22@digg.com",
      "gender": "Male",
      "city": "Kawanishi"
    },
    {
      "id": 76,
      "first_name": "Isis",
      "last_name": "Sollett",
      "email": "isollett23@google.co.uk",
      "gender": "Female",
      "city": "Villeurbanne"
    },
    {
      "id": 77,
      "first_name": "Any",
      "last_name": "Bachelar",
      "email": "abachelar24@mapquest.com",
      "gender": "Male",
      "city": "Santa Rita Aplaya"
    },
    {
      "id": 78,
      "first_name": "Neddie",
      "last_name": "Vere",
      "email": "nvere25@nbcnews.com",
      "gender": "Male",
      "city": "Alto Río Senguer"
    },
    {
      "id": 79,
      "first_name": "Lemar",
      "last_name": "Water",
      "email": "lwater26@xing.com",
      "gender": "Male",
      "city": "Narathiwat"
    },
    {
      "id": 80,
      "first_name": "Kelly",
      "last_name": "Gasken",
      "email": "kgasken27@examiner.com",
      "gender": "Female",
      "city": "Sharjah"
    },
    {
      "id": 81,
      "first_name": "Sax",
      "last_name": "Benedite",
      "email": "sbenedite28@china.com.cn",
      "gender": "Male",
      "city": "Dolní Počernice"
    },
    {
      "id": 82,
      "first_name": "Kalinda",
      "last_name": "Brockway",
      "email": "kbrockway29@google.co.jp",
      "gender": "Female",
      "city": "Tibiri"
    },
    {
      "id": 83,
      "first_name": "Linea",
      "last_name": "Benediktsson",
      "email": "lbenediktsson2a@hibu.com",
      "gender": "Female",
      "city": "Huangzhuang"
    },
    {
      "id": 84,
      "first_name": "Chico",
      "last_name": "Wolfindale",
      "email": "cwolfindale2b@arstechnica.com",
      "gender": "Male",
      "city": "Dimitsána"
    },
    {
      "id": 85,
      "first_name": "Viviene",
      "last_name": "Hug",
      "email": "vhug2c@mashable.com",
      "gender": "Female",
      "city": "Longmen"
    },
    {
      "id": 86,
      "first_name": "Rachael",
      "last_name": "Currell",
      "email": "rcurrell2d@boston.com",
      "gender": "Female",
      "city": "Chulabhorn"
    },
    {
      "id": 87,
      "first_name": "Meriel",
      "last_name": "Sidebotham",
      "email": "msidebotham2e@mail.ru",
      "gender": "Genderfluid",
      "city": "Dagupan"
    },
    {
      "id": 88,
      "first_name": "Jonas",
      "last_name": "Friel",
      "email": "jfriel2f@dot.gov",
      "gender": "Male",
      "city": "Jalgung"
    },
    {
      "id": 89,
      "first_name": "Zelda",
      "last_name": "Uttridge",
      "email": "zuttridge2g@uol.com.br",
      "gender": "Female",
      "city": "Longqiao"
    },
    {
      "id": 90,
      "first_name": "Henryetta",
      "last_name": "Kennerley",
      "email": "hkennerley2h@hp.com",
      "gender": "Female",
      "city": "San Luis Jilotepeque"
    },
    {
      "id": 91,
      "first_name": "Burgess",
      "last_name": "Codrington",
      "email": "bcodrington2i@ebay.com",
      "gender": "Male",
      "city": "Baltimore"
    },
    {
      "id": 92,
      "first_name": "Wynn",
      "last_name": "Scutts",
      "email": "wscutts2j@tinyurl.com",
      "gender": "Male",
      "city": "Sheksna"
    },
    {
      "id": 93,
      "first_name": "Noella",
      "last_name": "Gilfoy",
      "email": "ngilfoy2k@ft.com",
      "gender": "Female",
      "city": "Rothesay Bay"
    },
    {
      "id": 94,
      "first_name": "Candra",
      "last_name": "Roocroft",
      "email": "croocroft2l@liveinternet.ru",
      "gender": "Female",
      "city": "Bantilan"
    },
    {
      "id": 95,
      "first_name": "Tybi",
      "last_name": "Petofi",
      "email": "tpetofi2m@edublogs.org",
      "gender": "Female",
      "city": "Miandrarivo"
    },
    {
      "id": 96,
      "first_name": "Poul",
      "last_name": "Ferns",
      "email": "pferns2n@spotify.com",
      "gender": "Agender",
      "city": "Xiaojinkou"
    },
    {
      "id": 97,
      "first_name": "Clo",
      "last_name": "Filipczynski",
      "email": "cfilipczynski2o@php.net",
      "gender": "Female",
      "city": "Mēga"
    },
    {
      "id": 98,
      "first_name": "Anstice",
      "last_name": "Kramer",
      "email": "akramer2p@cdc.gov",
      "gender": "Female",
      "city": "Al Wajh"
    },
    {
      "id": 99,
      "first_name": "Emmerich",
      "last_name": "Leyshon",
      "email": "eleyshon2q@discovery.com",
      "gender": "Male",
      "city": "Loutrós"
    },
    {
      "id": 100,
      "first_name": "Kinnie",
      "last_name": "Danelutti",
      "email": "kdanelutti2r@shop-pro.jp",
      "gender": "Male",
      "city": "Tamansari"
    }
  ]
}
